experimenthub/__init__.py
experimenthub/_ehub.py
experimenthub/record.py
experimenthub/registry.py
experimenthub-0.0.1.dist-info/licenses/LICENSE.txt
experimenthub-0.0.1.dist-info/METADATA
experimenthub-0.0.1.dist-info/WHEEL
experimenthub-0.0.1.dist-info/top_level.txt
experimenthub-0.0.1.dist-info/RECORD
