Metadata-Version: 2.4
Name: experimenthub
Version: 0.0.1
Summary: Access Bioconductors experimenthub resources
Home-page: https://github.com/biocpy/experimenthub
Author: Jayaram Kancherla
Author-email: jayaram.kancherla@gmail.com
License: MIT
Project-URL: Documentation, https://github.com/biocpy/experimenthub
Project-URL: Source, https://github.com/biocpy/experimenthub
Platform: any
Classifier: Development Status :: 4 - Beta
Classifier: Programming Language :: Python
License-File: LICENSE.txt
Requires-Dist: importlib-metadata; python_version < "3.8"
Requires-Dist: rds2py
Requires-Dist: biocframe
Requires-Dist: pybiocfilecache
Provides-Extra: testing
Requires-Dist: setuptools; extra == "testing"
Requires-Dist: pytest; extra == "testing"
Requires-Dist: pytest-cov; extra == "testing"
Dynamic: license-file
